<?xml version="1.0" encoding="utf-8" ?>
<Dictionary>
  <Words>
    <Recognized>
      <Word>fullscreen</Word>
      <Word>framerate</Word>
      <Word>shader</Word>
      <Word>shaders</Word>
      <Word>png</Word>
      <Word>Renderables</Word>
      <Word>OmegaEngine</Word>
      <Word>PureDevice</Word>
      <Word>HardwareVertexProcessing</Word>
      <Word>SoftwareVertexProcessing</Word>
    </Recognized>
  </Words>
  <Acronyms>
    <CasingExceptions>
      <Acronym>OmegaEngine</Acronym>
      <Acronym>PureDevice</Acronym>
      <Acronym>HardwareVertexProcessing</Acronym>
      <Acronym>SoftwareVertexProcessing</Acronym>
    </CasingExceptions>
  </Acronyms>
</Dictionary>